mercury_api/__init__.py
mercury_api/app.py
mercury_api/configuration.py
mercury_api/custom_converters.py
mercury_api/decorators.py
mercury_api/exceptions.py
mercury_api/mercury_clients.py
mercury_api/server.py
mercury_api/transaction_log.py
mercury_api-0.1.3.dist-info/METADATA
mercury_api-0.1.3.dist-info/WHEEL
mercury_api-0.1.3.dist-info/entry_points.txt
mercury_api-0.1.3.dist-info/top_level.txt
mercury_api-0.1.3.dist-info/RECORD
