Metadata-Version: 2.1
Name: mercury-api
Version: 0.1.3
Summary: The mercury front end HTTP API
Home-page: https://www.rackspace.com
Author: Jared Rodriguez
Author-email: jared.rodriguez@rackspace.com
License: UNKNOWN
Platform: UNKNOWN
Requires-Dist: flask
Requires-Dist: pyzmq
Requires-Dist: msgpack-python
Requires-Dist: mercury-core
Requires-Dist: gevent
